ibm_watsonx_ai_120b/__init__.py
ibm_watsonx_ai_120b/config.py
ibm_watsonx_ai_120b/exceptions.py
ibm_watsonx_ai_120b/py.typed
ibm_watsonx_ai_120b/adapters/__init__.py
ibm_watsonx_ai_120b/adapters/harmony_adapter.py
ibm_watsonx_ai_120b/adapters/json_adapter.py
ibm_watsonx_ai_120b/adapters/message_adapter.py
ibm_watsonx_ai_120b/adapters/stream_adapter.py
ibm_watsonx_ai_120b/adapters/thinking_adapter.py
ibm_watsonx_ai_120b/adapters/tool_adapter.py
ibm_watsonx_ai_120b/foundation_models/__init__.py
ibm_watsonx_ai_120b/foundation_models/model_inference.py
ibm_watsonx_ai_120b/utils/__init__.py
ibm_watsonx_ai_120b/utils/json_repair.py
ibm_watsonx_ai_120b/utils/retry.py
ibm_watsonx_ai_120b/utils/tokens.py
ibm_watsonx_ai_120b-0.1.0.dist-info/METADATA
ibm_watsonx_ai_120b-0.1.0.dist-info/WHEEL
ibm_watsonx_ai_120b-0.1.0.dist-info/RECORD
