Metadata-Version: 2.4
Name: ibm-watsonx-ai-120b
Version: 0.1.0
Summary: Drop-in replacement for ibm-watsonx-ai that fixes vLLM bugs with gpt-oss-120b/20b models
Project-URL: Homepage, https://github.com/haroldhannon/ibm-watsonx-ai-120b
Project-URL: Documentation, https://github.com/haroldhannon/ibm-watsonx-ai-120b#readme
Project-URL: Repository, https://github.com/haroldhannon/ibm-watsonx-ai-120b
Project-URL: Issues, https://github.com/haroldhannon/ibm-watsonx-ai-120b/issues
Author: Harold Hannon
License-Expression: MIT
Keywords: ai,gpt-oss-120b,ibm,llm,machine-learning,vllm,watsonx
Classifier: Development Status :: 4 - Beta
Classifier: Intended Audience :: Developers
Classifier: License :: OSI Approved :: MIT License
Classifier: Operating System :: OS Independent
Classifier: Programming Language :: Python :: 3
Classifier: Programming Language :: Python :: 3.9
Classifier: Programming Language :: Python :: 3.10
Classifier: Programming Language :: Python :: 3.11
Classifier: Programming Language :: Python :: 3.12
Classifier: Topic :: Scientific/Engineering :: Artificial Intelligence
Classifier: Typing :: Typed
Requires-Python: >=3.9
Requires-Dist: ibm-watsonx-ai>=1.0.0
Requires-Dist: json-repair>=0.1.0
Requires-Dist: jsonschema>=4.0.0
Requires-Dist: tenacity>=8.0.0
Provides-Extra: dev
Requires-Dist: mypy>=1.0.0; extra == 'dev'
Requires-Dist: pytest-asyncio>=0.21.0; extra == 'dev'
Requires-Dist: pytest>=7.0.0; extra == 'dev'
Requires-Dist: responses>=0.23.0; extra == 'dev'
Requires-Dist: ruff>=0.1.0; extra == 'dev'
